credo/__init__.py
credo/modelresult.py
credo/modelrun.py
credo/modelsuite.py
credo/t2model.py
credo/utils.py
credo/waiwera.py
credo/analysis/__init__.py
credo/analysis/api.py
credo/analysis/fields.py
credo/analysis/images.py
credo/analysis/modelplots.py
credo/analysis/stats.py
credo/io/__init__.py
credo/io/stgcmdline.py
credo/io/stgcvg.py
credo/io/stgfreq.py
credo/io/stgpath.py
credo/io/stgxml.py
credo/jobrunner/__init__.py
credo/jobrunner/api.py
credo/jobrunner/pbsjobrunner.py
credo/jobrunner/simplejobrunner.py
credo/jobrunner/unixTimeCmdProfiler.py
credo/jobrunner/walltimeProfiler.py
credo/reporting/__init__.py
credo/reporting/reportGenerator.py
credo/reporting/reportLab.py
credo/reporting/rst.py
credo/reporting/standardReports.py
credo/systest/__init__.py
credo/systest/analyticMultiResTest.py
credo/systest/analyticTest.py
credo/systest/api.py
credo/systest/fieldCvgWithScaleTC.py
credo/systest/highResReferenceTest.py
credo/systest/imageCompTC.py
credo/systest/imageReferenceTest.py
credo/systest/outputWithinRangeTC.py
credo/systest/referenceTest.py
credo/systest/restartTest.py
credo/systest/sciBenchmarkTest.py
credo/systest/singleRunWithinTolTC.py
credo/systest/systestrunner.py
credo/systest/systestsuite.py
waiwera_credo-2.0.5.dist-info/COPYING.txt
waiwera_credo-2.0.5.dist-info/METADATA
waiwera_credo-2.0.5.dist-info/WHEEL
waiwera_credo-2.0.5.dist-info/top_level.txt
waiwera_credo-2.0.5.dist-info/RECORD
