Metadata-Version: 2.1
Name: waiwera-credo
Version: 2.0.5
Summary: Fork of CREDO computational model benchmarking toolkit, for use with the Waiwera geothermal flow simulator
Home-page: https://waiwera.github.io
Author: Waiwera Project
Author-email: waiwera.project@gmail.com
License: UNKNOWN
Platform: UNKNOWN
Classifier: Programming Language :: Python :: 2
Classifier: Programming Language :: Python :: 3
Classifier: License :: OSI Approved :: GNU Lesser General Public License v2 (LGPLv2)
Classifier: Operating System :: OS Independent
Requires-Python: >=2.7
Requires-Dist: future
Requires-Dist: matplotlib
Requires-Dist: scipy
Requires-Dist: Pillow
Requires-Dist: h5py
Requires-Dist: Shapely
Requires-Dist: docutils
Requires-Dist: reportlab
